confguard/__init__.py
confguard/__main__.py
confguard/adapter.py
confguard/environment.py
confguard/exceptions.py
confguard/helper.py
confguard/main.py
confguard/model.py
confguard-1.2.0.dist-info/AUTHORS
confguard-1.2.0.dist-info/LICENSE
confguard-1.2.0.dist-info/METADATA
confguard-1.2.0.dist-info/WHEEL
confguard-1.2.0.dist-info/entry_points.txt
confguard-1.2.0.dist-info/top_level.txt
confguard-1.2.0.dist-info/RECORD
