Metadata-Version: 2.1
Name: confguard
Version: 1.2.0
Summary: "Save configuration files outside project in save place"
Home-page: https://github.com/sysid/confguard
Author: sysid
Author-email: sysid@gmx.de
Classifier: Development Status :: 3 - Alpha
Classifier: Intended Audience :: Developers
Classifier: License :: OSI Approved :: BSD License
Classifier: Operating System :: OS Independent
Classifier: Programming Language :: Python :: 3
Classifier: Programming Language :: Python :: 3.9
Requires-Python: >=3.9
License-File: LICENSE
License-File: AUTHORS
Requires-Dist: pydantic
Requires-Dist: tomlkit
Requires-Dist: typer
Requires-Dist: rich
